CHANGELOG.md
majormode/__init__.py
majormode/perseus/__init__.py
majormode/perseus/constant/__init__.py
majormode/perseus/constant/email.py
majormode/perseus/email/__init__.py
majormode/perseus/email/email_service.py
majormode/perseus/email/provider/__init__.py
majormode/perseus/email/provider/gmail.py
majormode/perseus/email/provider/mailjet.py
majormode/perseus/model/__init__.py
majormode/perseus/model/email.py
perseus_email_library-1.0.28.dist-info/LICENSE
perseus_email_library-1.0.28.dist-info/WHEEL
perseus_email_library-1.0.28.dist-info/METADATA
perseus_email_library-1.0.28.dist-info/RECORD
